{"classTransform": {"Increased stability ": 1, "Reduced stability ": 0}, "matrixConfusionResponse": {"header": ["Reduced stability ", "Increased stability "], "fiabilidad": [100.0, 97.33333333333334], "matrix": [[57, 2], [0, 73]], "bakanosidad": [96.61016949152543, 100.0]}, "Params": {"n_estimators": "500", "min_samples_split": "2", "bootstrap": "True", "criterion": "gini", "min_samples_leaf": "1"}, "algorithm": "RandomForest", "errorExec": {"exec_algorithm": "OK", "confusionMatrix": "ok", "curveLearning": "ok"}, "Performance": {"f1": 0.9941176470588236, "recall": 1.0, "precision": 0.9888888888888889, "accuracy": 0.9845238095238095}, "Validation": "Cross Validation: 10", "scale_options": 2}